Metadata-Version: 2.1
Name: wicc
Version: 1.0.0
Summary: WaykiChain Wallet
Home-page: https://github.com/louishwh/
Author: louis han
Author-email: louishwh@gmail.com
License: UNKNOWN
Platform: UNKNOWN
Classifier: Programming Language :: Python :: 3
Classifier: License :: OSI Approved :: MIT License
Classifier: Operating System :: OS Independent
